MANIFEST.in
__init__.py
example_code128.py
example_datamatrix.py
example_ean13.py
example_qrcode.py
ez_setup.py
qrcode_generate_Data.py
setup.cfg
setup.py
barcodeserver/__init__.py
barcodeserver/manage.py
barcodeserver/manage_live.py
barcodeserver/settings.py
barcodeserver/settings_live.py
barcodeserver/setup.py
barcodeserver/urls.py
barcodeserver/api/__init__.py
barcodeserver/api/handlers.py
barcodeserver/api/urls.py
barcodeserver/barcodegui/__init__.py
barcodeserver/barcodegui/urls.py
code128/__init__.py
code128/code128test.py
code128/encoding.py
code128/generate_test.py
code128/renderer.py
code128/textencoder.py
datamatrix/__init__.py
datamatrix/matrixtest.py
datamatrix/placement.py
datamatrix/reedsolomon.py
datamatrix/renderer.py
datamatrix/textencoder.py
ean13/__init__.py
ean13/eantest.py
ean13/encoding.py
ean13/generate_test.py
ean13/renderer.py
huBarcode.egg-info/PKG-INFO
huBarcode.egg-info/SOURCES.txt
huBarcode.egg-info/dependency_links.txt
huBarcode.egg-info/not-zip-safe
huBarcode.egg-info/top_level.txt
qrcode/__init__.py
qrcode/isodata.py
qrcode/qrcodetest.py
qrcode/renderer.py
qrcode/textencoder.py
qrcode/qrdata/__init__.py
qrcode/qrdata/fr1.py
qrcode/qrdata/fr10.py
qrcode/qrdata/fr11.py
qrcode/qrdata/fr12.py
qrcode/qrdata/fr13.py
qrcode/qrdata/fr14.py
qrcode/qrdata/fr15.py
qrcode/qrdata/fr16.py
qrcode/qrdata/fr17.py
qrcode/qrdata/fr18.py
qrcode/qrdata/fr19.py
qrcode/qrdata/fr2.py
qrcode/qrdata/fr20.py
qrcode/qrdata/fr21.py
qrcode/qrdata/fr22.py
qrcode/qrdata/fr23.py
qrcode/qrdata/fr24.py
qrcode/qrdata/fr25.py
qrcode/qrdata/fr26.py
qrcode/qrdata/fr27.py
qrcode/qrdata/fr28.py
qrcode/qrdata/fr29.py
qrcode/qrdata/fr3.py
qrcode/qrdata/fr30.py
qrcode/qrdata/fr31.py
qrcode/qrdata/fr32.py
qrcode/qrdata/fr33.py
qrcode/qrdata/fr34.py
qrcode/qrdata/fr35.py
qrcode/qrdata/fr36.py
qrcode/qrdata/fr37.py
qrcode/qrdata/fr38.py
qrcode/qrdata/fr39.py
qrcode/qrdata/fr4.py
qrcode/qrdata/fr40.py
qrcode/qrdata/fr5.py
qrcode/qrdata/fr6.py
qrcode/qrdata/fr7.py
qrcode/qrdata/fr8.py
qrcode/qrdata/fr9.py
qrcode/qrdata/qrv10_0.py
qrcode/qrdata/qrv10_1.py
qrcode/qrdata/qrv10_2.py
qrcode/qrdata/qrv10_3.py
qrcode/qrdata/qrv11_0.py
