Metadata-Version: 1.0
Name: huBarcode
Version: 0.57
Summary: generation of barcodes in Python
Home-page: http://github.com/hudora/huBarcode
Author: Maximillian Dornseif
Author-email: md@hudora.de
License: UNKNOWN
Platform: UNKNOWN
Classifier: License :: OSI Approved :: BSD License
Classifier: Intended Audience :: Developers
Classifier: Programming Language :: Python
Classifier: Topic :: Multimedia :: Graphics
Classifier: Topic :: Office/Business
